{"end_avg_acc": 39.974444444444444, "end_avg_fgt": 45.589999999999996, "avg_cur_acc": 70.36777777777779, "Acc_across_runs": [[[99.12, 0.0, 0.0], [76.7, 30.0, 0.0], [20.8, 21.86, 81.96]], [[98.67, 0.0, 0.0], [67.11, 37.86, 0.0], [18.58, 24.14, 69.57]], [[99.71, 0.0, 0.0], [63.57, 34.0, 0.0], [23.01, 17.43, 82.42]]], "time_this_iter_s": 307.639267206192, "done": false, "timesteps_total": null, "episodes_total": null, "training_iteration": 1, "trial_id": "3aa01_00002", "experiment_id": "0757149c4f1d4dc4a118ef0769c349a1", "date": "2024-05-10_11-10-00", "timestamp": 1715310600, "time_total_s": 307.639267206192, "pid": 1463712, "hostname": "rinc1080ti-PR4764GW", "node_ip": "114.212.87.168", "config": {"generic": {"lr": 0.001, "lradj": "step15", "batch_size": 32, "weight_decay": 0}, "model": {"feature_dim": 128, "n_layers": 4, "dropout": 0.3}, "agent": {}}, "time_since_restore": 307.639267206192, "timesteps_since_restore": 0, "iterations_since_restore": 1, "warmup_time": 0.004909992218017578}
